rlbot_action_server/__init__.py
rlbot_action_server/__main__.py
rlbot_action_server/bot_action_broker.py
rlbot_action_server/bot_holder.py
rlbot_action_server/encoder.py
rlbot_action_server/formatting_utils.py
rlbot_action_server/typing_utils.py
rlbot_action_server/util.py
rlbot_action_server/controllers/__init__.py
rlbot_action_server/controllers/action_controller.py
rlbot_action_server/controllers/authorization_controller.py
rlbot_action_server/models/__init__.py
rlbot_action_server/models/action_choice.py
rlbot_action_server/models/api_response.py
rlbot_action_server/models/available_actions.py
rlbot_action_server/models/base_model_.py
rlbot_action_server/models/bot_action.py
rlbot_action_server/models/strategic_category.py
rlbot_action_server/swagger/swagger.yaml
rlbot_action_server/test/__init__.py
rlbot_action_server/test/test_action_controller.py
rlbot_action_server-1.1.0.dist-info/METADATA
rlbot_action_server-1.1.0.dist-info/WHEEL
rlbot_action_server-1.1.0.dist-info/entry_points.txt
rlbot_action_server-1.1.0.dist-info/top_level.txt
rlbot_action_server-1.1.0.dist-info/RECORD
