Metadata-Version: 2.1
Name: rlbot-action-server
Version: 1.1.0
Summary: Bot Action Server
Home-page: UNKNOWN
Author: UNKNOWN
Author-email: rlbotofficial@gmail.com
License: UNKNOWN
Keywords: Swagger,Bot Action Server
Platform: UNKNOWN
Requires-Dist: connexion
